px/__init__.py
px/lib.py
px/py.typed
px/cron/__init__.py
px/django/__init__.py
px/id/__init__.py
px/id/snowflakes.py
px/mq/__init__.py
px/rpc/__init__.py
px/sql/__init__.py
better_px-0.2.1.dist-info/METADATA
better_px-0.2.1.dist-info/WHEEL
better_px-0.2.1.dist-info/RECORD
